<?xml version="1.0" encoding="UTF-8"?>
<objects serializationModel="Studio.02.01.00">
	<object class="AudioFile" id="{c7963d35-cf13-489c-a131-e07d041f52d0}">
		<property name="assetPath">
			<value>song01.mp3</value>
		</property>
		<property name="isStreaming">
			<value>true</value>
		</property>
		<property name="frequencyInKHz">
			<value>48</value>
		</property>
		<property name="channelCount">
			<value>2</value>
		</property>
		<property name="length">
			<value>150.43199999999999</value>
		</property>
		<relationship name="masterAssetFolder">
			<destination>{0bc329bc-c828-422e-905d-05a699a5ba95}</destination>
		</relationship>
	</object>
</objects>
