<?xml version="1.0" encoding="UTF-8"?>
<objects serializationModel="Studio.02.02.00">
	<object class="EncodingSetting" id="{c18b4d42-6ed9-49b1-afe7-8481a0423536}">
		<property name="encodingFormat">
			<value>3</value>
		</property>
		<property name="quality">
			<value>37</value>
		</property>
		<relationship name="platform">
			<destination>{da4ad819-7327-4ae2-a753-bec5ac41f88c}</destination>
		</relationship>
		<relationship name="encodable">
			<destination>{da4ad819-7327-4ae2-a753-bec5ac41f88c}</destination>
		</relationship>
	</object>
</objects>
